{"paths": {"/providers/{id}": {"get": {"summary": "Fetches a provider by its ID", "description": "Endpoint that retrieves provider by ID", "parameters": [{"in": "path", "name": "id", "description": "id of provider to get", "schema": {"type": "integer"}, "required": true}], "tags": ["providers"], "responses": {"200": {"description": "OK"}, "404": {"description": "Not found", "code": 5}}}, "patch": {"summary": "Updates a provider resource by ID", "description": "Endpoint that updates a provider by id", "tags": ["providers"], "consumes": ["application/json"], "produces": ["application/json"], "parameters": [{"in": "path", "name": "id", "schema": {"type": "integer"}, "description": "id of provider to patch", "required": true}], "requestBody": {"description": "Object that contains key *name*", "required": true, "content": {"application/json": {"schema": {"type": "object", "properties": {"name": {"type": "string"}}, "required": ["name"]}}}}, "responses": {"200": {"description": "OK"}, "400": {"description": "Bad request", "code": 3}, "404": {"description": "Not found", "code": 5}}}}, "/providers": {"get": {"summary": "Fetches every existent provider", "description": "Endpoint that retrieves every providers", "tags": ["providers"], "responses": {"200": {"description": "OK"}}}, "post": {"summary": "Creates a provider resource", "description": "Endpoint that creates a provider", "tags": ["providers"], "consumes": ["application/json"], "produces": ["application/json"], "requestBody": {"description": "Object that contains key *name*", "required": true, "content": {"application/json": {"schema": {"type": "object", "properties": {"name": {"type": "string"}}, "required": ["name"]}}}}, "responses": {"201": {"description": "Created"}, "400": {"description": "Bad request", "code": 2}}}}, "/providers/{id}/wallet": {"get": {"summary": "Fetches a wallet by its provider id", "description": "Endpoint that gets a wallet by its provider id", "tags": ["wallets"], "consumes": ["application/json"], "produces": ["application/json"], "parameters": [{"in": "path", "name": "id", "description": "id of provider", "schema": {"type": "integer"}, "required": true}], "responses": {"200": {"description": "OK"}, "404": {"description": "Not Found", "code": 2}}}, "post": {"summary": "Creates a wallet for a certain provider", "description": "Endpoint that creates a wallet for a specified provider id", "tags": ["wallets"], "consumes": ["application/json"], "produces": ["application/json"], "parameters": [{"in": "path", "name": "id", "description": "id of provider", "schema": {"type": "integer"}, "required": true}], "requestBody": {"description": "Object that contains key *entropy*", "required": true, "content": {"application/json": {"schema": {"type": "object", "properties": {"entropy": {"type": "string"}}, "required": ["entropy"]}}}}, "responses": {"201": {"description": "Created"}, "400": {"description": "Bad request", "code": 2}, "404": {"description": "Not Found", "code": 5}}}}, "/wallets": {"get": {"summary": "Fetches every existent wallet", "description": "Endpoint that retrieves every wallet", "tags": ["wallets"], "responses": {"200": {"description": "OK"}}}}, "/infrastructures/{id}": {"get": {"summary": "Fetches an infrastructure by  ID", "description": "Endpoint that retrieves infrastructure by  ID", "parameters": [{"in": "path", "name": "id", "description": "id of infrastructure", "schema": {"type": "integer"}, "required": true}], "tags": ["infrastructures"], "responses": {"200": {"description": "OK"}, "404": {"description": "Not found"}}}}, "/infrastructures": {"get": {"summary": "Fetches every existent infrastructure", "description": "Endpoint that retrieves every infrastructure", "tags": ["infrastructures"], "responses": {"200": {"description": "OK"}}}}, "/providers/{id}/infrastructures": {"get": {"summary": "Fetches an infrastructure by its provider's ID", "description": "Endpoint that retrieves infrastructure by its provider's ID", "parameters": [{"in": "path", "name": "id", "description": "id of provider", "schema": {"type": "integer"}, "required": true}], "tags": ["infrastructures"], "responses": {"200": {"description": "OK"}, "404": {"description": "Not found"}}}, "post": {"summary": "Creates an infrastructure resource", "description": "Endpoint that creates an infrastructure", "tags": ["infrastructures"], "consumes": ["application/json"], "produces": ["application/json"], "parameters": [{"in": "path", "name": "id", "description": "id of provider that creates infrastructure", "schema": {"type": "integer"}, "required": true}], "requestBody": {"description": "Object that contains keys to create infrastructure", "required": true, "content": {"application/json": {"schema": {"type": "object", "properties": {"vicinity_oid": {"type": "string"}, "longitude": {"type": "number"}, "latitude": {"type": "number"}, "name": {"type": "string"}}, "required": ["vicinity_oid", "longitude", "latitude", "name"]}}}}, "responses": {"201": {"description": "Created"}, "400": {"description": "Bad request"}, "404": {"description": "Not Found"}}}}, "/providers/{id}/pricingcontract": {"get": {"summary": "Fetches pricing contract by its ID", "description": "Endpoint that retrieves pricing contract by ID", "parameters": [{"in": "path", "name": "id", "description": "id of pricing contract", "schema": {"type": "integer"}, "required": true}], "tags": ["pricing_contracts"], "responses": {"200": {"description": "OK"}, "404": {"description": "Not found"}}}, "post": {"summary": "Creates a pricing contract to a provider's id", "description": "Endpoint that creates pricing contract", "tags": ["pricing_contracts"], "consumes": ["application/json"], "produces": ["application/json"], "parameters": [{"in": "path", "name": "id", "schema": {"type": "integer"}, "description": "id of provider to create pricing contract", "required": true}], "requestBody": {"description": "Object that contains key *initial_price*", "required": true, "content": {"application/json": {"schema": {"type": "object", "properties": {"initial_price": {"type": "integer"}}, "required": ["initial_price"]}}}}, "responses": {"200": {"description": "OK"}, "400": {"description": "Bad request"}, "404": {"description": "Not found"}}}}, "/pricingcontracts": {"get": {"summary": "Fetches every existent pricing contract", "description": "Endpoint that retrieves every pricing contract", "tags": ["pricing_contracts"], "responses": {"200": {"description": "OK"}}}}, "/providers/{id}/rate": {"get": {"summary": "Fetches a rate practiced by provider's ID", "description": "Endpoint that retrieves rate", "parameters": [{"in": "path", "name": "id", "description": "id of provider", "schema": {"type": "integer"}, "required": true}], "tags": ["price_rate"], "responses": {"200": {"description": "OK"}, "404": {"description": "Not found"}}}, "patch": {"summary": "Updates the price practiced by provider' id", "description": "Endpoint that updates price", "tags": ["price_rate"], "consumes": ["application/json"], "produces": ["application/json"], "parameters": [{"in": "path", "name": "id", "schema": {"type": "integer"}, "description": "id of provider", "required": true}], "requestBody": {"description": "Object that contains key *price_rate*", "required": true, "content": {"application/json": {"schema": {"type": "object", "properties": {"price_rate": {"type": "integer"}}, "required": ["price_rate"]}}}}, "responses": {"200": {"description": "OK"}, "400": {"description": "Bad request"}, "404": {"description": "Not found"}}}}, "/providers/{id}/discount": {"get": {"summary": "Fetches the discount practiced by provider's ID", "description": "Endpoint that retrieves discount", "parameters": [{"in": "path", "name": "id", "description": "id of provider", "schema": {"type": "integer"}, "required": true}], "tags": ["discount_rate"], "responses": {"200": {"description": "OK"}, "404": {"description": "Not found"}}}, "patch": {"summary": "Updates the discount practiced by provider's id", "description": "Endpoint that updates discount", "tags": ["discount_rate"], "consumes": ["application/json"], "produces": ["application/json"], "parameters": [{"in": "path", "name": "id", "schema": {"type": "integer"}, "description": "id of provider", "required": true}], "requestBody": {"description": "Object that contains key *discount_rate*", "required": true, "content": {"application/json": {"schema": {"type": "object", "properties": {"discount_rate": {"type": "integer"}}, "required": ["discount_rate"]}}}}, "responses": {"200": {"description": "OK"}, "400": {"description": "Bad request"}, "404": {"description": "Not found"}}}}, "/transaction/start": {"post": {"summary": "Creates the start of a transaction", "description": "Endpoint that creates the beginning of a transaction", "tags": ["transactions"], "consumes": ["application/json"], "produces": ["application/json"], "requestBody": {"description": "Object that contains key object to start transaction", "required": true, "content": {"application/json": {"schema": {"type": "object", "properties": {"idTag": {"type": "string"}, "meterValue": {"type": "integer"}, "vicinityOid": {"type": "string"}}, "required": ["idTag", "meterValue", "vicinityOid"]}}}}, "responses": {"201": {"description": "Created"}, "400": {"description": "Bad request"}, "404": {"description": "Not Found"}}}}, "/transaction/stop": {"post": {"summary": "Creates the stop of a transaction", "description": "Endpoint that creates the finish of a transaction", "tags": ["transactions"], "consumes": ["application/json"], "produces": ["application/json"], "requestBody": {"description": "Object that contains key object to start transaction", "required": true, "content": {"application/json": {"schema": {"type": "object", "properties": {"idTag": {"type": "string"}, "meterValue": {"type": "integer"}, "vicinityOid": {"type": "string"}}, "required": ["idTag", "meterValue", "vicinityOid"]}}}}, "responses": {"201": {"description": "Created"}, "400": {"description": "Bad request"}, "404": {"description": "Not Found"}}}}, "/metervalue": {"put": {"summary": "Updates the metervalue of the tx", "description": "Endpoint that updates the metervalue", "tags": ["transactions"], "consumes": ["application/json"], "produces": ["application/json"], "requestBody": {"description": "Object that contains key object to start transaction", "required": true, "content": {"application/json": {"schema": {"type": "object", "properties": {"idTag": {"type": "string"}, "meterValue": {"type": "integer"}, "vicinityOid": {"type": "string"}}, "required": ["idTag", "meterValue", "vicinityOid"]}}}}, "responses": {"201": {"description": "Created"}, "400": {"description": "Bad request"}, "404": {"description": "Not Found"}}}}}, "info": {"title": "MSP API documentation", "version": "0.0.1"}, "openapi": "3.0.2"}